tellimer/__init__.py
tellimer/_clients/_articles.py
tellimer/_clients/_client.py
tellimer/_clients/_data.py
tellimer/_clients/_news.py
tellimer/_clients/_probability_default.py
tellimer/_models.py
tellimer/errors.py
tellimer/py.typed
tellimer/types.py
tellimer-0.2.5.dist-info/WHEEL
tellimer-0.2.5.dist-info/METADATA
tellimer-0.2.5.dist-info/RECORD
