Metadata-Version: 2.3
Name: tellimer
Version: 0.2.5
Summary: Python SDK for the Tellimer API
Author: Justin Godden
Author-email: Justin Godden <justin.godden@tellimer.com>
Requires-Dist: httpx==0.24.1
Requires-Dist: pandas>=2.0.0
Requires-Dist: tenacity>=9.1.2
Requires-Python: >=3.10
